{
  "m_GameObject": {
    "m_FileID": 0,
    "m_PathID": 0
  },
  "m_Enabled": 1,
  "m_Script": {
    "m_FileID": 0,
    "m_PathID": -3977807471082417869
  },
  "m_Name": "IconLockList00",
  "savePath": 1,
  "isEnableCheckNoEmptyValue": 0,
  "assetDataList": [
    {
      "obj": {
        "m_FileID": 0,
        "m_PathID": 0
      },
      "path": "Assets/Main/Content/UI/Texture/IconLock00.png",
      "guid": "b384329d87c1fb14d9ded68e3b29d31b",
      "substitutedArrayIndex": 0
    },
    {
      "obj": {
        "m_FileID": 0,
        "m_PathID": 0
      },
      "path": "Assets/Main/Content/UI/Texture/IconLock01.png",
      "guid": "7fee861c8c9f7674b96268d92c8aa4ff",
      "substitutedArrayIndex": 1
    }
  ],
  "assetType": 0,
  "keyType": 0
}