{
  "m_GameObject": {
    "m_FileID": 0,
    "m_PathID": 0
  },
  "m_Enabled": 1,
  "m_Script": {
    "m_FileID": 0,
    "m_PathID": 6390104249597991665
  },
  "m_Name": "RaceRank45thList00",
  "savePath": 1,
  "isEnableCheckNoEmptyValue": 0,
  "assetDataList": [
    {
      "obj": {
        "m_FileID": 0,
        "m_PathID": 0
      },
      "path": "Assets/Main/Content/UI/Texture/Text/RaceRank/RaceRank45thJPja.png",
      "guid": "4899c6cbb444ad64c9975518f00f00f2",
      "substitutedArrayIndex": 0
    },
    {
      "obj": {
        "m_FileID": 0,
        "m_PathID": 0
      },
      "path": "",
      "guid": "",
      "substitutedArrayIndex": 0
    },
    {
      "obj": {
        "m_FileID": 0,
        "m_PathID": 0
      },
      "path": "",
      "guid": "",
      "substitutedArrayIndex": 1
    },
    {
      "obj": {
        "m_FileID": 0,
        "m_PathID": 0
      },
      "path": "Assets/Main/Content/UI/Texture/Text/RaceRank/RaceRank45thUSes.png",
      "guid": "c24aa8f848f2a654b83ad0f6a50fe7e4",
      "substitutedArrayIndex": 0
    },
    {
      "obj": {
        "m_FileID": 0,
        "m_PathID": 0
      },
      "path": "",
      "guid": "",
      "substitutedArrayIndex": 3
    },
    {
      "obj": {
        "m_FileID": 0,
        "m_PathID": 0
      },
      "path": "",
      "guid": "",
      "substitutedArrayIndex": 1
    },
    {
      "obj": {
        "m_FileID": 0,
        "m_PathID": 0
      },
      "path": "Assets/Main/Content/UI/Texture/Text/RaceRank/RaceRank45thEUfr.png",
      "guid": "aa3322f63371f6a4db9840084898f3c8",
      "substitutedArrayIndex": 0
    },
    {
      "obj": {
        "m_FileID": 0,
        "m_PathID": 0
      },
      "path": "Assets/Main/Content/UI/Texture/Text/RaceRank/RaceRank45thEUde.png",
      "guid": "6cc03980d8298e144b45ad6e60a7a334",
      "substitutedArrayIndex": 0
    },
    {
      "obj": {
        "m_FileID": 0,
        "m_PathID": 0
      },
      "path": "",
      "guid": "",
      "substitutedArrayIndex": 11
    },
    {
      "obj": {
        "m_FileID": 0,
        "m_PathID": 0
      },
      "path": "",
      "guid": "",
      "substitutedArrayIndex": 1
    },
    {
      "obj": {
        "m_FileID": 0,
        "m_PathID": 0
      },
      "path": "",
      "guid": "",
      "substitutedArrayIndex": 1
    },
    {
      "obj": {
        "m_FileID": 0,
        "m_PathID": 0
      },
      "path": "Assets/Main/Content/UI/Texture/Text/RaceRank/RaceRank45thUSpt.png",
      "guid": "d08c5165042df7343868bc26f64aa8be",
      "substitutedArrayIndex": 0
    },
    {
      "obj": {
        "m_FileID": 0,
        "m_PathID": 0
      },
      "path": "",
      "guid": "",
      "substitutedArrayIndex": 0
    },
    {
      "obj": {
        "m_FileID": 0,
        "m_PathID": 0
      },
      "path": "",
      "guid": "",
      "substitutedArrayIndex": 0
    },
    {
      "obj": {
        "m_FileID": 0,
        "m_PathID": 0
      },
      "path": "",
      "guid": "",
      "substitutedArrayIndex": 0
    }
  ]
}