{
  "m_GameObject": {
    "m_FileID": 0,
    "m_PathID": 0
  },
  "m_Enabled": 1,
  "m_Script": {
    "m_FileID": 0,
    "m_PathID": -3205259396417638272
  },
  "m_Name": "TireK_Slick_Black",
  "mTireType": 0,
  "mTireList": [],
  "mIconInfo": [
    {
      "mPath": "",
      "mGuid": ""
    }
  ],
  "mIsFixedIcon": 0,
  "mBaseParameter": {
    "m_FileID": 1,
    "m_PathID": -1938059995075122969
  },
  "mMaterial": {
    "m_FileID": 2,
    "m_PathID": 8833662594882392159
  },
  "mShaftMaterial": {
    "m_FileID": 0,
    "m_PathID": 0
  },
  "mEffectContainer": {
    "m_FileID": 0,
    "m_PathID": 0
  },
  "mEffectContainerForBody": [],
  "mDescription": "スリックタイヤ（黒）",
  "mColorValiationRoot": {
    "m_FileID": 1,
    "m_PathID": -1938059995075122969
  }
}