{
  "m_GameObject": {
    "m_FileID": 0,
    "m_PathID": 0
  },
  "m_Enabled": 1,
  "m_Script": {
    "m_FileID": 0,
    "m_PathID": -3977807471082417869
  },
  "m_Name": "TutorialGuideListAll00",
  "savePath": 1,
  "isEnableCheckNoEmptyValue": 0,
  "assetDataList": [
    {
      "obj": {
        "m_FileID": 0,
        "m_PathID": 7419557492806049253
      },
      "path": "",
      "guid": "",
      "substitutedArrayIndex": 0
    },
    {
      "obj": {
        "m_FileID": 0,
        "m_PathID": 4335197018965753614
      },
      "path": "",
      "guid": "",
      "substitutedArrayIndex": 1
    },
    {
      "obj": {
        "m_FileID": 0,
        "m_PathID": 607955169790806336
      },
      "path": "",
      "guid": "",
      "substitutedArrayIndex": 2
    },
    {
      "obj": {
        "m_FileID": 0,
        "m_PathID": 6780118870469973276
      },
      "path": "",
      "guid": "",
      "substitutedArrayIndex": 3
    },
    {
      "obj": {
        "m_FileID": 0,
        "m_PathID": -3878848663307445786
      },
      "path": "",
      "guid": "",
      "substitutedArrayIndex": 4
    }
  ],
  "assetType": 2,
  "keyType": 0
}